humanmodels/HumanClassifier.py
humanmodels/HumanRegressor.py
humanmodels/__init__.py
humanmodels/_humanmodels.py
humanmodels-0.5.9.dist-info/LICENSE
humanmodels-0.5.9.dist-info/METADATA
humanmodels-0.5.9.dist-info/WHEEL
humanmodels-0.5.9.dist-info/top_level.txt
humanmodels-0.5.9.dist-info/RECORD
